chisel/__init__.py
chisel/action.py
chisel/app.py
chisel/doc.py
chisel/request.py
chisel/static/__init__.py
chisel/static/chiselDoc.bare
chisel/static/index.html
chisel/static/markdown-up.tar.gz
chisel-1.9.23.dist-info/licenses/LICENSE
chisel-1.9.23.dist-info/METADATA
chisel-1.9.23.dist-info/WHEEL
chisel-1.9.23.dist-info/top_level.txt
chisel-1.9.23.dist-info/RECORD
