Metadata-Version: 2.4
Name: chisel
Version: 1.9.23
Summary: Lightweight WSGI application framework, schema-validated JSON APIs, and API documentation
Home-page: https://github.com/craigahobbs/chisel
Author: Craig A. Hobbs
Author-email: craigahobbs@gmail.com
License: MIT
Keywords: api,json,framework,schema,wsgi
Classifier: Development Status :: 5 - Production/Stable
Classifier: Intended Audience :: Developers
Classifier: Operating System :: OS Independent
Classifier: Programming Language :: Python :: 3.10
Classifier: Programming Language :: Python :: 3.11
Classifier: Programming Language :: Python :: 3.12
Classifier: Programming Language :: Python :: 3.13
Classifier: Programming Language :: Python :: 3.14
Classifier: Topic :: Internet :: WWW/HTTP :: WSGI
Classifier: Topic :: Internet :: WWW/HTTP :: WSGI :: Application
Classifier: Topic :: Software Development :: Libraries :: Application Frameworks
License-File: LICENSE
Requires-Dist: schema-markdown>=1.2.0
Dynamic: license-file
